dfdata/__init__.py
dfdata/default_config.py
dfdata/del_data.py
dfdata/info_data.py
dfdata/read_data.py
dfdata/save_data.py
dfdata/source/__init__.py
dfdata/source/collect/__init__.py
dfdata/source/collect/default_config.py
dfdata/source/collect/futures/__init__.py
dfdata/source/collect/futures/consts.py
dfdata/source/collect/futures/exchange_abroad.py
dfdata/source/collect/futures/exchange_china.py
dfdata/source/collect/futures/futures.py
dfdata/source/collect/stock/__init__.py
dfdata/source/collect/stock/cn_sse.py
dfdata/source/collect/stock/consts.py
dfdata/source/jqdata/__init__.py
dfdata/source/jqdata/default_config.py
dfdata/source/jqdata/futures.py
dfdata/source/tushare/__init__.py
dfdata/source/tushare/default_config.py
dfdata/source/tushare/futures.py
dfdata/source/tushare/stock.py
dfdata/util/__init__.py
dfdata/util/config.py
dfdata/util/db_tool.py
dfdata/util/func_tool.py
dfdata/util/log.py
tests/__init__.py
tests/test_func.py
tests/test_nor.py
dfdata-0.0.6.dist-info/LICENSE
dfdata-0.0.6.dist-info/METADATA
dfdata-0.0.6.dist-info/WHEEL
dfdata-0.0.6.dist-info/top_level.txt
dfdata-0.0.6.dist-info/RECORD
