Metadata-Version: 2.1
Name: dfdata
Version: 0.0.6
Summary: 下载金融数据
Home-page: https://github.com/dfdata/dfdata
Author: dfdata
Author-email: dfdata@outlook.com
License: UNKNOWN
Platform: UNKNOWN
Classifier: Programming Language :: Python :: 3
Classifier: License :: OSI Approved :: MIT License
Classifier: Operating System :: OS Independent
Requires-Python: >=3.6
License-File: LICENSE
